h2o_nitro_web/__init__.py
h2o_nitro_web/version.py
h2o_nitro_web/www/asset-manifest.json
h2o_nitro_web/www/favicon.ico
h2o_nitro_web/www/image.png
h2o_nitro_web/www/index.html
h2o_nitro_web/www/sample.jpg
h2o_nitro_web/www/styles.css
h2o_nitro_web/www/assets/fonts/Inter-Black-cyrillic-ext.woff2
h2o_nitro_web/www/assets/fonts/Inter-Black-cyrillic.woff2
h2o_nitro_web/www/assets/fonts/Inter-Black-greek-ext.woff2
h2o_nitro_web/www/assets/fonts/Inter-Black-greek.woff2
h2o_nitro_web/www/assets/fonts/Inter-Black-latin-ext.woff2
h2o_nitro_web/www/assets/fonts/Inter-Black-latin.woff2
h2o_nitro_web/www/assets/fonts/Inter-Black-vietnamese.woff2
h2o_nitro_web/www/assets/fonts/Inter-ExtraBold-cyrillic-ext.woff2
h2o_nitro_web/www/assets/fonts/Inter-ExtraBold-cyrillic.woff2
h2o_nitro_web/www/assets/fonts/Inter-ExtraBold-greek-ext.woff2
h2o_nitro_web/www/assets/fonts/Inter-ExtraBold-greek.woff2
h2o_nitro_web/www/assets/fonts/Inter-ExtraBold-latin-ext.woff2
h2o_nitro_web/www/assets/fonts/Inter-ExtraBold-latin.woff2
h2o_nitro_web/www/assets/fonts/Inter-ExtraBold-vietnamese.woff2
h2o_nitro_web/www/assets/fonts/Inter-ExtraLight-cyrillic-ext.woff2
h2o_nitro_web/www/assets/fonts/Inter-ExtraLight-cyrillic.woff2
h2o_nitro_web/www/assets/fonts/Inter-ExtraLight-greek-ext.woff2
h2o_nitro_web/www/assets/fonts/Inter-ExtraLight-greek.woff2
h2o_nitro_web/www/assets/fonts/Inter-ExtraLight-latin-ext.woff2
h2o_nitro_web/www/assets/fonts/Inter-ExtraLight-latin.woff2
h2o_nitro_web/www/assets/fonts/Inter-ExtraLight-vietnamese.woff2
h2o_nitro_web/www/assets/fonts/Inter-Inter-Bold-cyrillic-ext.woff2
h2o_nitro_web/www/assets/fonts/Inter-Inter-Bold-cyrillic.woff2
h2o_nitro_web/www/assets/fonts/Inter-Inter-Bold-greek-ext.woff2
h2o_nitro_web/www/assets/fonts/Inter-Inter-Bold-greek.woff2
h2o_nitro_web/www/assets/fonts/Inter-Inter-Bold-latin-ext.woff2
h2o_nitro_web/www/assets/fonts/Inter-Inter-Bold-latin.woff2
h2o_nitro_web/www/assets/fonts/Inter-Inter-Bold-vietnamese.woff2
h2o_nitro_web-0.21.1.dist-info/LICENSE
h2o_nitro_web-0.21.1.dist-info/METADATA
h2o_nitro_web-0.21.1.dist-info/WHEEL
h2o_nitro_web-0.21.1.dist-info/top_level.txt
h2o_nitro_web-0.21.1.dist-info/RECORD
